partyai/__init__.py
partyai/partyai.py
partyai-0.0.2.dist-info/METADATA
partyai-0.0.2.dist-info/WHEEL
partyai-0.0.2.dist-info/top_level.txt
partyai-0.0.2.dist-info/RECORD
