Metadata-Version: 2.1
Name: partyai
Version: 0.0.2
Summary: Functions for ChatGPT
Home-page: https://github.com/partyai/partyai
Author: Imad Bouziani
Author-email: imad.a.bouziani@gmail.com
License: MIT
Classifier: License :: OSI Approved :: MIT License
Classifier: Programming Language :: Python :: 3
Classifier: Programming Language :: Python :: 3.9
Requires-Dist: requests
